fabric_datalake_manager/__init__.py
fabric_datalake_manager/datalake_manager.py
fabric_datalake_manager/dataclass/__init__.py
fabric_datalake_manager/dataclass/bronze_dataclass.py
fabric_datalake_manager/dataclass/gold_dataclass.py
fabric_datalake_manager/dataclass/silver_dataclass.py
fabric_datalake_manager/datapoints/__init__.py
fabric_datalake_manager/datapoints/bronze_datapoint.py
fabric_datalake_manager/datapoints/gold_datapoint.py
fabric_datalake_manager/datapoints/silver_datapoint.py
fabric_datalake_manager/datapoints/warehouse_datapoint.py
fabric_datalake_manager/enums/__init__.py
fabric_datalake_manager/enums/enum.py
fabric_datalake_manager/ingestion_models/__init__.py
fabric_datalake_manager/ingestion_models/app_config.py
fabric_datalake_manager/ingestion_models/connection_information.py
fabric_datalake_manager/ingestion_models/ingested_data.py
fabric_datalake_manager/ingestion_models/source_data.py
fabric_datalake_manager/interfaces/__init__.py
fabric_datalake_manager/interfaces/config_interface.py
fabric_datalake_manager/interfaces/datapoint_interface.py
fabric_datalake_manager/interfaces/ingest_interface.py
fabric_datalake_manager/interfaces/log_interface.py
fabric_datalake_manager/interfaces/transform_interface.py
fabric_datalake_manager/interfaces/validate_interface.py
fabric_datalake_manager/layer_configs/__init__.py
fabric_datalake_manager/layer_configs/bronze_config.py
fabric_datalake_manager/layer_configs/gold_config.py
fabric_datalake_manager/layer_configs/silver_config.py
fabric_datalake_manager/loggers/__init__.py
fabric_datalake_manager/loggers/logger_executor.py
fabric_datalake_manager/loggers/slack_logger.py
fabric_datalake_manager-0.1.31.dist-info/METADATA
fabric_datalake_manager-0.1.31.dist-info/WHEEL
fabric_datalake_manager-0.1.31.dist-info/top_level.txt
fabric_datalake_manager-0.1.31.dist-info/RECORD
