Metadata-Version: 2.4
Name: fabric_datalake_manager
Version: 0.1.31
Summary: A Fabric extension for managing data lakes
Author: Mahmudul Hasan Roni
Requires-Python: >=3.11
Requires-Dist: dacite>=1.9.2
Requires-Dist: adlfs
Dynamic: author
Dynamic: description-content-type
Dynamic: requires-dist
Dynamic: requires-python
Dynamic: summary
